aria/__cli__.py
aria/__gen2_cli__.py
aria/__init__.py
aria/_version.py
aria/aria-cli
aria/aria_gen2_cli
aria/aria_streaming_viewer.py
aria/doctor.py
aria/extract_sdk_samples.py
aria/image_decoder.py
aria/libomp.so
aria/libsdk_core.so
aria/oss_data_converter.py
aria/sdk.cpython-311-x86_64-linux-gnu.so
aria/sdk.pyi
aria/sdk_gen2.cpython-311-x86_64-linux-gnu.so
aria/setup.py
aria/stream_receiver.py
aria/diagnostics/diagnostics.py
aria/diagnostics/diagnostics_adb_controller.py
aria/diagnostics/diagnostics_streaming_handlers.py
aria/diagnostics/linux_platform_info.py
aria/diagnostics/mac_platform_info.py
aria/diagnostics/platform_info.py
aria/diagnostics/utils.py
aria/gen2_samples/AriaRaw.msg
aria/gen2_samples/device_auth.py
aria/gen2_samples/device_connect.py
aria/gen2_samples/device_raw_streaming.py
aria/gen2_samples/device_record.py
aria/gen2_samples/device_streaming.py
aria/gen2_samples/device_tts.py
aria/gen2_samples/ros2_publisher_example.py
aria/gen2_samples/ros2_subscriber_example.py
aria/samples/README.md
aria/samples/common.py
aria/samples/device_auth.py
aria/samples/device_connect.py
aria/samples/device_record.py
aria/samples/device_stream.py
aria/samples/requirements.txt
aria/samples/streaming_start.py
aria/samples/streaming_subscribe.py
aria/samples/undistort_rgb_image.py
aria/samples/visualizer.py
aria/samples/ticsync/ticsync_cleanup.py
aria/samples/ticsync/ticsync_file_manager.py
aria/samples/ticsync/ticsync_recording.py
aria/samples/ticsync/ticsync_verifier.py
aria/tools/adb
projectaria_client_sdk-2.1.0.dist-info/METADATA
projectaria_client_sdk-2.1.0.dist-info/WHEEL
projectaria_client_sdk-2.1.0.dist-info/entry_points.txt
projectaria_client_sdk-2.1.0.dist-info/top_level.txt
projectaria_client_sdk-2.1.0.dist-info/RECORD
