Metadata-Version: 2.1
Name: projectaria-client-sdk
Version: 2.1.0
Summary: Project Aria Client SDK For Python
Author: Meta
Requires-Dist: numpy
Requires-Dist: projectaria-tools==2.1.0
Requires-Dist: setuptools
Requires-Dist: termcolor
